wadda/__init__.py
wadda/main.py
wadda/pypcd/__init__.py
wadda/pypcd/nea_pc_format.py
wadda/pypcd/numpy_pc2.py
wadda/pypcd/pdutil.py
wadda/pypcd/pypcd.py
wadda/pypcd/sautil.py
wadda/pypcd/version.py
wadda/tools/__init__.py
wadda/tools/data_collection/__init__.py
wadda/tools/data_collection/data_recorder.py
wadda/tools/data_collection/main.py
wadda/tools/data_collection/parse_config.py
wadda/tools/data_collection/ros_dataset.py
wadda/tools/data_collection/utils.py
wadda/tools/gif_generator/__init__.py
wadda/tools/gif_generator/main.py
wadda/tools/pcd_visualizer/__init__.py
wadda/tools/pcd_visualizer/main.py
wadda/tools/ros_visualizer/__init__.py
wadda/tools/ros_visualizer/main.py
wadda/tools/voc2coco/__init__.py
wadda/tools/voc2coco/main.py
wadda-0.0.5.dist-info/LICENSE
wadda-0.0.5.dist-info/METADATA
wadda-0.0.5.dist-info/WHEEL
wadda-0.0.5.dist-info/entry_points.txt
wadda-0.0.5.dist-info/top_level.txt
wadda-0.0.5.dist-info/RECORD
